[  {    "type": "post",    "url": "/books/add",    "title": "Add new Book",    "name": "Add_new_Book",    "version": "0.0.1",    "group": "Books",    "parameter": {      "fields": {        "Parameter": [          {            "group": "Parameter",            "type": "String",            "optional": false,            "field": "Author",            "description": "<p>Author of the book to be created.</p>"          },          {            "group": "Parameter",            "type": "String",            "optional": false,            "field": "Title",            "description": "<p>Title of the book to be created.</p>"          },          {            "group": "Parameter",            "type": "String",            "optional": false,            "field": "Summary",            "description": "<p>Summary of the book to be created.</p>"          }        ]      }    },    "success": {      "fields": {        "Success 200": [          {            "group": "Success 200",            "type": "String",            "optional": false,            "field": "msg",            "description": "<p>Status Message</p>"          }        ]      }    },    "error": {      "fields": {        "Error 4xx": [          {            "group": "Error 4xx",            "type": "String",            "optional": false,            "field": "error",            "description": "<p>Error Message</p>"          }        ]      }    },    "filename": "routes/books.js",    "groupTitle": "Books"  },  {    "type": "delete",    "url": "/books/:bookId",    "title": "Delete existing Book",    "name": "Delete_Existing_Book",    "version": "0.0.1",    "group": "Books",    "success": {      "fields": {        "Success 200": [          {            "group": "Success 200",            "type": "String",            "optional": false,            "field": "msg",            "description": "<p>Status Message</p>"          }        ]      }    },    "error": {      "fields": {        "Error 4xx": [          {            "group": "Error 4xx",            "type": "String",            "optional": false,            "field": "error",            "description": "<p>Error Message</p>"          }        ]      }    },    "filename": "routes/books.js",    "groupTitle": "Books"  },  {    "type": "get",    "url": "/books/:bookId",    "title": "Get Single book",    "name": "Get_Single_book",    "version": "0.0.1",    "group": "Books",    "success": {      "fields": {        "Success 200": [          {            "group": "Success 200",            "type": "Array",            "optional": false,            "field": "data",            "description": "<p>{ &quot;author&quot;: &quot;Shona Rhimes &quot;, &quot;title&quot;: &quot;Jack and Jill&quot;, &quot;summary&quot;: &quot;This was the best book i have read&quot;, &quot;id&quot;: &quot;2&quot; }</p>"          }        ]      }    },    "error": {      "fields": {        "Error 4xx": [          {            "group": "Error 4xx",            "type": "String",            "optional": false,            "field": "error",            "description": "<p>Error Message</p>"          }        ]      }    },    "filename": "routes/books.js",    "groupTitle": "Books"  },  {    "type": "get",    "url": "/books",    "title": "Get all books",    "name": "Get_all_books",    "version": "0.0.1",    "group": "Books",    "success": {      "fields": {        "Success 200": [          {            "group": "Success 200",            "type": "Array",            "optional": false,            "field": "data",            "description": "<p>[{ &quot;author&quot;: &quot;davidsonss stew&quot;, &quot;title&quot;: &quot;aliqweqwrw&quot;, &quot;summary&quot;: &quot;sing and shout&quot;, &quot;id&quot;: &quot;2&quot; },{ &quot;author&quot;: &quot;davidsonss stew&quot;, &quot;title&quot;: &quot;aliqweqwrw&quot;, &quot;summary&quot;: &quot;sing and shout&quot;, &quot;id&quot;: &quot;1&quot; }]</p>"          }        ]      }    },    "error": {      "fields": {        "Error 4xx": [          {            "group": "Error 4xx",            "type": "String",            "optional": false,            "field": "error",            "description": "<p>Error Message</p>"          }        ]      }    },    "filename": "routes/books.js",    "groupTitle": "Books"  },  {    "type": "put",    "url": "/books/:bookId",    "title": "Update existing Book",    "name": "Update_Existing_Book",    "version": "0.0.1",    "group": "Books",    "parameter": {      "fields": {        "Parameter": [          {            "group": "Parameter",            "type": "String",            "optional": false,            "field": "Author",            "description": "<p>Author to be updated.</p>"          },          {            "group": "Parameter",            "type": "String",            "optional": false,            "field": "Title",            "description": "<p>Title to be updated.</p>"          },          {            "group": "Parameter",            "type": "String",            "optional": false,            "field": "Summary",            "description": "<p>Summary to be updated.</p>"          }        ]      }    },    "success": {      "fields": {        "Success 200": [          {            "group": "Success 200",            "type": "String",            "optional": false,            "field": "msg",            "description": "<p>Status Message</p>"          }        ]      }    },    "error": {      "fields": {        "Error 4xx": [          {            "group": "Error 4xx",            "type": "String",            "optional": false,            "field": "error",            "description": "<p>Error Message</p>"          }        ]      }    },    "filename": "routes/books.js",    "groupTitle": "Books"  }]
